easynotes/__init__.py
easynotes/calc.py
easynotes/cut.py
easynotes/easynotes.py
easynotes/easypymanager.py
easynotes/mind.py
easynotes/notes.py
easynotes/task.py
easynotes-1.2.7.dist-info/LICENSE
easynotes-1.2.7.dist-info/METADATA
easynotes-1.2.7.dist-info/WHEEL
easynotes-1.2.7.dist-info/entry_points.txt
easynotes-1.2.7.dist-info/top_level.txt
easynotes-1.2.7.dist-info/RECORD
