Metadata-Version: 2.1
Name: easynotes
Version: 1.2.7
Summary: EasyNotes is a Python tool designed for note-taking, mind mapping, reminders, and running Python scripts. 
Author: sysucai
Author-email: 411703730@qq.com
Platform: Any platform -- don't need Windows
Classifier: Programming Language :: Python :: 3
Classifier: License :: OSI Approved :: MIT License
Classifier: Operating System :: OS Independent
Requires-Python: >=3.7
License-File: LICENSE
Requires-Dist: PyQt5 >=0.0.1
